dclustval/__init__.py
dclustval/cluster.py
dclustval-0.1.0.dist-info/LICENSE
dclustval-0.1.0.dist-info/METADATA
dclustval-0.1.0.dist-info/WHEEL
dclustval-0.1.0.dist-info/top_level.txt
dclustval-0.1.0.dist-info/RECORD
